codat/__init__.py
codat/company_management.py
codat/configuration.py
codat/integrations.py
codat/sdk.py
codat/sync.py
codat/sync_flow_preferences.py
codat/models/__init__.py
codat/models/operations/__init__.py
codat/models/operations/create_company.py
codat/models/operations/create_connection.py
codat/models/operations/get_config_text_sync_flow.py
codat/models/operations/get_configuration.py
codat/models/operations/get_integration_branding.py
codat/models/operations/get_sync_flow_url.py
codat/models/operations/get_sync_status.py
codat/models/operations/get_visible_accounts.py
codat/models/operations/list_companies.py
codat/models/operations/list_connections.py
codat/models/operations/list_integrations.py
codat/models/operations/request_sync.py
codat/models/operations/request_sync_for_date_range.py
codat/models/operations/set_configuration.py
codat/models/operations/update_config_text_sync_flow.py
codat/models/operations/update_connection.py
codat/models/operations/update_visible_accounts_sync_flow.py
codat/models/shared/__init__.py
codat/models/shared/accountoption.py
codat/models/shared/companies.py
codat/models/shared/company.py
codat/models/shared/configaccount.py
codat/models/shared/configuration.py
codat/models/shared/connection.py
codat/models/shared/connections.py
codat/models/shared/createcompany.py
codat/models/shared/customer.py
codat/models/shared/dataconnectionerror.py
codat/models/shared/dataconnectionstatus_enum.py
codat/models/shared/datatypefeature.py
codat/models/shared/daterange.py
codat/models/shared/featurestate_enum.py
codat/models/shared/featuretype_enum.py
codat/models/shared/fees.py
codat/models/shared/feessupplier.py
codat/models/shared/grouping.py
codat/models/shared/groupinglevels.py
codat/models/shared/groupingperiod.py
codat/models/shared/halref.py
codat/models/shared/integration.py
codat/models/shared/integrations.py
codat/models/shared/invoicelevelselection.py
codat/models/shared/invoicelinelevelselection.py
codat_synccommerce-0.8.5.dist-info/METADATA
codat_synccommerce-0.8.5.dist-info/WHEEL
codat_synccommerce-0.8.5.dist-info/top_level.txt
codat_synccommerce-0.8.5.dist-info/RECORD
